secretmessage/__init__.py
secretmessage-0.3.dist-info/LICENSE.txt
secretmessage-0.3.dist-info/METADATA
secretmessage-0.3.dist-info/WHEEL
secretmessage-0.3.dist-info/top_level.txt
secretmessage-0.3.dist-info/RECORD
