Metadata-Version: 2.1
Name: secretmessage
Version: 0.3
Summary: For generating Messages Secretly.
Author: E Lusifa Taehyung
Author-email: purplebird7613@gmail.com
Classifier: Programming Language :: Python
Classifier: License :: OSI Approved :: MIT License
Classifier: Operating System :: OS Independent
License-File: LICENSE.txt
